neon_tts_plugin_polly/__init__.py
neon_tts_plugin_polly/util/__init__.py
neon_tts_plugin_polly-0.2.0.dist-info/LICENSE.md
neon_tts_plugin_polly-0.2.0.dist-info/METADATA
neon_tts_plugin_polly-0.2.0.dist-info/WHEEL
neon_tts_plugin_polly-0.2.0.dist-info/entry_points.txt
neon_tts_plugin_polly-0.2.0.dist-info/top_level.txt
neon_tts_plugin_polly-0.2.0.dist-info/zip-safe
neon_tts_plugin_polly-0.2.0.dist-info/RECORD
