Metadata-Version: 2.1
Name: neon-tts-plugin-polly
Version: 0.2.0
Summary: A Polly TTS plugin for Neon
Home-page: https://github.com/NeonGeckoCom/neon-tts-plugin-polly
Author: Neongecko
Author-email: developers@neon.ai
License: NeonAI License v1.0
Keywords: mycroft plugin tts
Platform: UNKNOWN
Classifier: Intended Audience :: Developers
Classifier: Topic :: Text Processing :: Linguistic
Classifier: Programming Language :: Python :: 3.6
Requires-Dist: boto3 (~=1.15)
Requires-Dist: ovos-plugin-manager (~=0.0.2)
Requires-Dist: ovos-utils (~=0.0.15)
